diogobaeder.webfaction-0.0.6-py3.6-nspkg.pth
diogobaeder/webfaction/__init__.py
diogobaeder/webfaction/tools.py
diogobaeder.webfaction-0.0.6.dist-info/DESCRIPTION.rst
diogobaeder.webfaction-0.0.6.dist-info/METADATA
diogobaeder.webfaction-0.0.6.dist-info/RECORD
diogobaeder.webfaction-0.0.6.dist-info/WHEEL
diogobaeder.webfaction-0.0.6.dist-info/metadata.json
diogobaeder.webfaction-0.0.6.dist-info/namespace_packages.txt
diogobaeder.webfaction-0.0.6.dist-info/top_level.txt
diogobaeder.webfaction-0.0.6.dist-info/zip-safe
