Metadata-Version: 2.0
Name: diogobaeder.webfaction
Version: 0.0.6
Summary: Tools to help with deploying to Webfaction
Home-page: https://github.com/diogobaeder/diogobaeder.webfaction
Author: Diogo Baeder
Author-email: diogobaeder@yahoo.com.br
License: BSD 2-Clause License
Keywords: diogobaeder webfaction python django
Platform: UNKNOWN
Classifier: Programming Language :: Python :: 3
Requires-Dist: cryptography
Requires-Dist: Fabric3
Requires-Dist: keyring
Requires-Dist: keyrings.alt
Requires-Dist: SecretStorage
Requires-Dist: setuptools-scm
Requires-Dist: wfcli
